{
  "2f265bc8": {
    "id": "2f265bc8",
    "ref": "罗马书1:8",
    "versions": {
      "cuv": "第一，我靠着耶稣基督，为你们众人感谢我的神，因你们的信德传遍了天下。",
      "ccb": "（暂无当代译本）",
      "esv": "(ESV not available)"
    }
  },
  "f10c36ec": {
    "id": "f10c36ec",
    "ref": "罗马书1:11",
    "versions": {
      "cuv": "因为我切切地想见你们，要把些属灵的恩赐分给你们，使你们可以坚固。",
      "ccb": "（暂无当代译本）",
      "esv": "(ESV not available)"
    }
  },
  "3386406f": {
    "id": "3386406f",
    "ref": "罗马书1:12-13",
    "versions": {
      "cuv": "弟兄们，我不愿意你们不知道，我屡次定意要往你们那里去，在你们中间得些果子。",
      "ccb": "（暂无当代译本）",
      "esv": "(ESV not available)"
    }
  },
  "e55f55b8": {
    "id": "e55f55b8",
    "ref": "雅各书1:2",
    "versions": {
      "cuv": "我的弟兄们，你们落在百般试炼中，都要以为大喜乐；",
      "ccb": "（暂无当代译本）",
      "esv": "(ESV not available)"
    }
  },
  "8fdbdb25": {
    "id": "8fdbdb25",
    "ref": "罗马书1:10",
    "versions": {
      "cuv": "在祷告之间常常恳求，或者照神的旨意，终能得平坦的道路往你们那里去。",
      "ccb": "（暂无当代译本）",
      "esv": "(ESV not available)"
    }
  },
  "0244922f": {
    "id": "0244922f",
    "ref": "雅各书4:13-15",
    "versions": {
      "cuv": "你们有话说：“今天明天我们要往某城里去，在那里住一年，做买卖得利。”其实明天如何，你们还不知道。你们的生命是什么呢？你们原来是一片云雾，出现少时就不见了。你们只当说：“主若愿意，我们就可以活着，也可以做这事，或做那事。",
      "ccb": "（暂无当代译本）",
      "esv": "(ESV not available)"
    }
  },
  "2c677cea": {
    "id": "2c677cea",
    "ref": "使徒行传 16:6-7 和合本",
    "versions": {
      "cuv": "圣灵既然禁止他们在亚细亚讲道，他们就经过弗吕家、加拉太一带地方。到了每西亚的边界，他们想要往庇推尼去，耶稣的灵却不许。",
      "ccb": "（暂无当代译本）",
      "esv": "(ESV not available)"
    }
  }
}